README.md
setup.cfg
setup.py
dsnd_probability_dk/Binomialdistribution.py
dsnd_probability_dk/Gaussiandistribution.py
dsnd_probability_dk/Generaldistribution.py
dsnd_probability_dk/__init__.py
dsnd_probability_dk.egg-info/PKG-INFO
dsnd_probability_dk.egg-info/SOURCES.txt
dsnd_probability_dk.egg-info/dependency_links.txt
dsnd_probability_dk.egg-info/not-zip-safe
dsnd_probability_dk.egg-info/top_level.txt