Metadata-Version: 1.0
Name: dsnd-probability-dk
Version: 0.2
Summary: Gaussian and Binomial distributions
Home-page: UNKNOWN
Author: Daur Rahymzhan
Author-email: daur.rahymzhan@gmail.com
License: UNKNOWN
Platform: UNKNOWN
